microservice_maker/1_docker-compose.yml.py
microservice_maker/2_docker-entrypoint.sh.py
microservice_maker/3_env.py
microservice_maker/4_Dockerfile.py
microservice_maker/5_req.py
microservice_maker/__init__.py
microservice_maker/django_maker.py
microservice_maker/flask_maker.py
microservice_maker/logo.py
microservice_maker/main.py
microservice_maker/main_ui.py
microservice_maker/teste.ui.py
microservice_maker/ui-django.ui.py
microservice_maker/ui_django.py
microservice_maker/ui_main.py
microservice_maker-0.7.2.data/scripts/make-microservice
microservice_maker-0.7.2.dist-info/LICENSE.txt
microservice_maker-0.7.2.dist-info/METADATA
microservice_maker-0.7.2.dist-info/WHEEL
microservice_maker-0.7.2.dist-info/dependency_links.txt
microservice_maker-0.7.2.dist-info/top_level.txt
microservice_maker-0.7.2.dist-info/RECORD
