Metadata-Version: 2.1
Name: microservice-maker
Version: 0.7.2
Summary: Lib to create python microservices with django and flask
Home-page: https://gitlab.com/victorhdcoelho/make_django
Author: Victor Coelho
Author-email: victorhdcoelho@gmail.com
License: UNKNOWN
Platform: UNKNOWN
Classifier: Programming Language :: Python :: 3
Classifier: License :: OSI Approved :: MIT License
Classifier: Operating System :: OS Independent
Requires-Python: >=3.6
License-File: LICENSE.txt
Requires-Dist: PySimpleGUI
Requires-Dist: tqdm
